README
s3domain.py
setup.py
s3domain.egg-info/PKG-INFO
s3domain.egg-info/SOURCES.txt
s3domain.egg-info/dependency_links.txt
s3domain.egg-info/entry_points.txt
s3domain.egg-info/requires.txt
s3domain.egg-info/top_level.txt
s3domain.egg-info/zip-safe