Metadata-Version: 1.0
Name: s3domain
Version: 1.0.1
Summary: Script for creating a new s3 bucket with webhosting turned on.
Home-page: http://dryan.github.io/s3domain
Author: Daniel Ryan
Author-email: dryan@dryan.com
License: MIT License
Platform: UNKNOWN
